hydra_plugins/__init__.py
hydra_plugins/additional_searchpath.py
hydra_plugins/test/__init__.py
hydra_plugins/test/algorithms/override_agent.yaml
hydra_plugins/test/harness/override_harness.yaml
hydra_plugins/test/test_config.yaml
sail_on_client/__init__.py
sail_on_client/agent/__init__.py
sail_on_client/agent/condda_agent.py
sail_on_client/agent/mock_condda_agents.py
sail_on_client/agent/mock_ond_agents.py
sail_on_client/agent/ond_agent.py
sail_on_client/agent/ond_reaction_agent.py
sail_on_client/agent/pre_computed_detector.py
sail_on_client/agent/pre_computed_reaction_agent.py
sail_on_client/agent/visual_agent.py
sail_on_client/aggregate_features.py
sail_on_client/checkpointer.py
sail_on_client/client_launcher.py
sail_on_client/configs/__init__.py
sail_on_client/configs/algorithms/__init__.py
sail_on_client/configs/algorithms/pre_computed_condda_agent.yaml
sail_on_client/configs/algorithms/pre_computed_ond_agent.yaml
sail_on_client/configs/algorithms/pre_computed_ond_reaction_agent.yaml
sail_on_client/configs/base/__init__.py
sail_on_client/configs/base/base_condda.yaml
sail_on_client/configs/base/base_ond.yaml
sail_on_client/configs/default.yaml
sail_on_client/configs/harness/__init__.py
sail_on_client/configs/harness/local.yaml
sail_on_client/configs/harness/par.yaml
sail_on_client/configs/protocol/__init__.py
sail_on_client/configs/protocol/condda.yaml
sail_on_client/configs/protocol/detection/__init__.py
sail_on_client/configs/protocol/detection/given.yaml
sail_on_client/configs/protocol/detection/system.yaml
sail_on_client/configs/protocol/eval/__init__.py
sail_on_client/configs/protocol/eval/none.yaml
sail_on_client/configs/protocol/eval/with_reaction.yaml
sail_on_client/configs/protocol/eval/without_reaction.yaml
sail_on_client/configs/protocol/feedback/__init__.py
sail_on_client/configs/protocol/feedback/classification.yaml
sail_on_client/configs/protocol/feedback/detection.yaml
sail_on_client/configs/protocol/feedback/detection_and_classification.yaml
sail_on_client-0.30.0.dist-info/entry_points.txt
sail_on_client-0.30.0.dist-info/LICENSE
sail_on_client-0.30.0.dist-info/WHEEL
sail_on_client-0.30.0.dist-info/METADATA
sail_on_client-0.30.0.dist-info/RECORD
