Metadata-Version: 2.1
Name: sail-on-client
Version: 0.30.0
Summary: Client and Protocols for DARPA sail-on
License: Apache-2.0
Author: Ameya Shringi
Author-email: ameya.shringi@kitware.com
Requires-Python: >=3.7,<4.0
Classifier: License :: OSI Approved :: Apache Software License
Classifier: Programming Language :: Python :: 3
Classifier: Programming Language :: Python :: 3.10
Classifier: Programming Language :: Python :: 3.7
Classifier: Programming Language :: Python :: 3.8
Classifier: Programming Language :: Python :: 3.9
Requires-Dist: hydra-colorlog (>=1.1.0,<2.0.0)
Requires-Dist: hydra-core (>=1.1.1,<2.0.0)
Requires-Dist: importlib-metadata (>=1.6.0)
Requires-Dist: matplotlib (>=3.2.2,<4.0.0)
Requires-Dist: nltk (>=3.6.7,<4.0.0)
Requires-Dist: numpy (>=1.18.3)
Requires-Dist: pandas (>=1.0.3)
Requires-Dist: requests (>=2.23.0)
Requires-Dist: scriptconfig (==0.5.6)
Requires-Dist: tenacity (>=7.0.0,<8.0.0)
Requires-Dist: tinker-engine (>=0.10.1,<0.11.0)
Requires-Dist: torch (>=1.6.0,<2.0.0)
Requires-Dist: tqdm (>=4.64.0,<5.0.0)
Requires-Dist: types-dataclasses (>=0.6.4,<0.7.0)
Requires-Dist: ubelt (==0.9.2)
